sparkmanager/__init__.py
sparkmanager/eventlog.py
sparkmanager/manager.py
sparkmanager-0.7.1.data/scripts/sm_cluster
sparkmanager-0.7.1.data/scripts/sm_run
sparkmanager-0.7.1.data/scripts/sm_shutdown
sparkmanager-0.7.1.data/scripts/sm_startup
sparkmanager-0.7.1.dist-info/LICENSE
sparkmanager-0.7.1.dist-info/METADATA
sparkmanager-0.7.1.dist-info/WHEEL
sparkmanager-0.7.1.dist-info/top_level.txt
sparkmanager-0.7.1.dist-info/RECORD
