Metadata-Version: 2.1
Name: sparkmanager
Version: 0.7.1
Summary: A pyspark management framework
Home-page: https://github.com/matz-e/sparkmanager
Author: Matthias Wolf
Author-email: matthias.wolf@epfl.ch
License: MIT
Keywords: apache-spark
Platform: UNKNOWN
Classifier: Development Status :: 3 - Alpha
Classifier: License :: OSI Approved :: MIT License
Classifier: Programming Language :: Python :: 2
Classifier: Programming Language :: Python :: 3
Classifier: Topic :: Software Development :: Libraries
Requires-Dist: pyspark
Requires-Dist: six
